spade/__init__.py
spade/agent.py
spade/behaviour.py
spade/cli.py
spade/container.py
spade/message.py
spade/presence.py
spade/template.py
spade/trace.py
spade/web.py
spade/xmpp_client.py
spade/templates/internal_tpl_agent.html
spade/templates/internal_tpl_base.html
spade/templates/internal_tpl_behaviour.html
spade/templates/internal_tpl_index.html
spade/templates/internal_tpl_macros.html
spade/templates/internal_tpl_messages.html
spade-4.0.1.dist-info/AUTHORS.rst
spade-4.0.1.dist-info/LICENSE
spade-4.0.1.dist-info/METADATA
spade-4.0.1.dist-info/WHEEL
spade-4.0.1.dist-info/entry_points.txt
spade-4.0.1.dist-info/top_level.txt
spade-4.0.1.dist-info/RECORD
