Metadata-Version: 2.1
Name: spade
Version: 4.0.1
Summary: Smart Python Agent Development Environment
Home-page: https://github.com/javipalanca/spade
Author: Javi Palanca
Author-email: jpalanca@gmail.com
Maintainer: Javi Palanca
License: MIT
Project-URL: Homepage, https://github.com/javipalanca/spade
Project-URL: Repository, https://github.com/javipalanca/spade
Keywords: spade
Classifier: Development Status :: 5 - Production/Stable
Classifier: Intended Audience :: Developers
Classifier: License :: OSI Approved :: MIT License
Classifier: Natural Language :: English
Classifier: Programming Language :: Python :: 3
Classifier: Programming Language :: Python :: 3.8
Classifier: Programming Language :: Python :: 3.9
Classifier: Programming Language :: Python :: 3.10
Classifier: Programming Language :: Python :: 3.11
Classifier: Programming Language :: Python :: 3.12
Classifier: Operating System :: MacOS :: MacOS X
Classifier: Operating System :: POSIX :: Linux
Classifier: Operating System :: Microsoft :: Windows
Classifier: Topic :: Scientific/Engineering :: Artificial Intelligence
Classifier: Topic :: Internet :: XMPP
License-File: LICENSE
License-File: AUTHORS.rst
Requires-Dist: slixmpp==1.8.5
Requires-Dist: aiohttp>=3.10.4
Requires-Dist: aiohttp_jinja2==1.6
Requires-Dist: jinja2==3.0.3
Requires-Dist: jinja2-time==0.2.0
Requires-Dist: timeago==1.0.16
Requires-Dist: singletonify==0.2.4
Requires-Dist: pytz==2022.1
Requires-Dist: pyjabber>=0.1.9
Requires-Dist: rich>=13.9.4
Requires-Dist: uvloop>=0.21.0; platform_system != "Windows"
Requires-Dist: winloop>=0.1.7; platform_system == "Windows"
